{
  "id": "leccion-42",
  "titulo": "Lesson 42: Sounds /or/ and /aw/",
  "edad_objetivo": 3,
  "guion_padre": {
    "introduccion": "Welcome to Lesson 42. Today we will explore some wonderful sounds.",
    "instruccion_or": "Point to the big OR and say: ororor. Keep the sound going!",
    "instruccion_aw": "Now point to the big AW and say: awawaw."
  },
  "parent_story": "A bear held a fork. A bird flew over the storm in the forest.",
  "ejercicios_nino": [
    {
      "id": "ej-42-01",
      "tipo": "letra_gigante",
      "letra": "OR",
      "color": "bg-orange-500",
      "sonido": "ororor",
      "words": [
        {
          "word": "Fork",
          "emoji": "🍴"
        },
        {
          "word": "Storm",
          "emoji": "⛈️"
        }
      ]
    },
    {
      "id": "ej-42-02",
      "tipo": "letra_gigante",
      "letra": "AW",
      "color": "bg-red-500",
      "sonido": "awawaw",
      "words": [
        {
          "word": "Straw",
          "emoji": "🥤"
        },
        {
          "word": "Claw",
          "emoji": "🦖"
        }
      ]
    }
  ]
}